tabulate.py
tabulate-0.8.10.dist-info/LICENSE
tabulate-0.8.10.dist-info/METADATA
tabulate-0.8.10.dist-info/WHEEL
tabulate-0.8.10.dist-info/entry_points.txt
tabulate-0.8.10.dist-info/top_level.txt
tabulate-0.8.10.dist-info/RECORD
